automation_test_with_submodule/__init__.py
automation_test_with_submodule/api_client.py
automation_test_with_submodule/api_response.py
automation_test_with_submodule/apis/__init__.py
automation_test_with_submodule/apis/path_to_api.py
automation_test_with_submodule/apis/paths/__init__.py
automation_test_with_submodule/apis/paths/hello.py
automation_test_with_submodule/apis/tag_to_api.py
automation_test_with_submodule/apis/tags/__init__.py
automation_test_with_submodule/apis/tags/greetings_api.py
automation_test_with_submodule/apis/tags/greetings_api_generated.py
automation_test_with_submodule/apis/tags/greetings_api_raw.py
automation_test_with_submodule/client.py
automation_test_with_submodule/client.pyi
automation_test_with_submodule/client_custom.py
automation_test_with_submodule/configuration.py
automation_test_with_submodule/exceptions.py
automation_test_with_submodule/exceptions_base.py
automation_test_with_submodule/model/__init__.py
automation_test_with_submodule/model/hello_response.py
automation_test_with_submodule/model/hello_response.pyi
automation_test_with_submodule/models/__init__.py
automation_test_with_submodule/operation_parameter_map.py
automation_test_with_submodule/paths/__init__.py
automation_test_with_submodule/paths/hello/__init__.py
automation_test_with_submodule/paths/hello/get.py
automation_test_with_submodule/paths/hello/get.pyi
automation_test_with_submodule/pydantic/__init__.py
automation_test_with_submodule/pydantic/hello_response.py
automation_test_with_submodule/request_after_hook.py
automation_test_with_submodule/request_before_hook.py
automation_test_with_submodule/request_before_url_hook.py
automation_test_with_submodule/rest.py
automation_test_with_submodule/schemas.py
automation_test_with_submodule/type/__init__.py
automation_test_with_submodule/type/hello_response.py
automation_test_with_submodule/type_util.py
automation_test_with_submodule/validation_metadata.py
automation_test_with_submodule_python_sdk-1.0.11.dist-info/LICENSE
automation_test_with_submodule_python_sdk-1.0.11.dist-info/METADATA
automation_test_with_submodule_python_sdk-1.0.11.dist-info/WHEEL
automation_test_with_submodule_python_sdk-1.0.11.dist-info/RECORD
